Scorpii/__init__.py
Scorpii/file2.py
Scorpii/number.py
Scorpii/time2.py
Scorpii-0.0.1.dist-info/LICENCE
Scorpii-0.0.1.dist-info/METADATA
Scorpii-0.0.1.dist-info/WHEEL
Scorpii-0.0.1.dist-info/top_level.txt
Scorpii-0.0.1.dist-info/RECORD
