Metadata-Version: 2.1
Name: Scorpii
Version: 0.0.1
Summary: A package full of useful features
Home-page: https://github.com/Oscar-Hogben/Scorpii
Author: Oscar Hogben
Author-email: oscarhogben@gmail.com
Project-URL: Bug Tracker, https://github.com/Oscar-Hogben/Scorpii/issues
Classifier: Programming Language :: Python :: 3
Classifier: License :: OSI Approved :: MIT License
Classifier: Operating System :: OS Independent
Requires-Python: >=3.6
License-File: LICENCE
